pbshm/__init__.py
pbshm/db.py
pbshm/authentication/__init__.py
pbshm/authentication/authentication.py
pbshm/authentication/templates/login.html
pbshm/initialisation/__init__.py
pbshm/initialisation/initialisation.py
pbshm/initialisation/user-schema.json
pbshm/layout/__init__.py
pbshm/layout/layout.py
pbshm/layout/static/logo.png
pbshm/layout/static/style.css
pbshm/layout/templates/base.html
pbshm/layout/templates/home.html
pbshm/layout/templates/portal.html
pbshm/mechanic/__init__.py
pbshm/mechanic/mechanic.py
pbshm/timekeeper/__init__.py
pbshm/timekeeper/timekeeper.py
pbshm_core-1.1.6.dist-info/licenses/LICENSE
pbshm_core-1.1.6.dist-info/METADATA
pbshm_core-1.1.6.dist-info/WHEEL
pbshm_core-1.1.6.dist-info/top_level.txt
pbshm_core-1.1.6.dist-info/RECORD
