Metadata-Version: 2.4
Name: pbshm-core
Version: 1.1.6
Summary: PBSHM Core Library
Author-email: Dan Brennan <d.s.brennan@sheffield.ac.uk>
License:                     GNU AFFERO GENERAL PUBLIC LICENSE
Project-URL: homepage, https://github.com/dynamics-research-group/pbshm-flask-core
Classifier: License :: OSI Approved :: GNU Affero General Public License v3 or later (AGPLv3+)
Classifier: Programming Language :: Python :: 3
Classifier: Framework :: Flask
Requires-Python: >=3.9.18
License-File: LICENSE
Requires-Dist: Flask==3.1.1
Requires-Dist: Werkzeug==3.1.3
Requires-Dist: pymongo==4.13.2
Requires-Dist: pytz==2022.6
Dynamic: license-file
